{
  "__inputs": [
    {
      "name": "DS_GRAPHITE",
      "label": "Graphite",
      "description": "",
      "type": "datasource",
      "pluginId": "graphite",
      "pluginName": "Graphite"
    }
  ],
  "__elements": {},
  "__requires": [
    {
      "type": "grafana",
      "id": "grafana",
      "name": "Grafana",
      "version": "10.0.2"
    },
    {
      "type": "datasource",
      "id": "graphite",
      "name": "Graphite",
      "version": "1.0.0"
    },
    {
      "type": "panel",
      "id": "timeseries",
      "name": "Time series",
      "version": ""
    }
  ],
  "annotations": {
    "list": [
      {
        "builtIn": 1,
        "datasource": {
          "type": "datasource",
          "uid": "grafana"
        },
        "enable": true,
        "hide": true,
        "iconColor": "rgba(0, 211, 255, 1)",
        "name": "Annotations & Alerts",
        "target": {
          "limit": 100,
          "matchAny": false,
          "tags": [],
          "type": "dashboard"
        },
        "type": "dashboard"
      }
    ]
  },
  "editable": true,
  "fiscalYearStartMonth": 0,
  "graphTooltip": 0,
  "id": null,
  "links": [],
  "liveNow": false,
  "panels": [
    {
      "datasource": {
        "type": "graphite",
        "uid": "$Datasource"
      },
      "fieldConfig": {
        "defaults": {
          "color": {
            "mode": "palette-classic"
          },
          "custom": {
            "axisCenteredZero": false,
            "axisColorMode": "text",
            "axisLabel": "",
            "axisPlacement": "auto",
            "barAlignment": 0,
            "drawStyle": "line",
            "fillOpacity": 0,
            "gradientMode": "none",
            "hideFrom": {
              "legend": false,
              "tooltip": false,
              "viz": false
            },
            "lineInterpolation": "linear",
            "lineWidth": 1,
            "pointSize": 5,
            "scaleDistribution": {
              "type": "linear"
            },
            "showPoints": "never",
            "spanNulls": false,
            "stacking": {
              "group": "A",
              "mode": "none"
            },
            "thresholdsStyle": {
              "mode": "off"
            }
          },
          "mappings": [],
          "thresholds": {
            "mode": "absolute",
            "steps": [
              {
                "color": "green",
                "value": null
              },
              {
                "color": "red",
                "value": 80
              }
            ]
          },
          "unit": "µs"
        },
        "overrides": []
      },
      "gridPos": {
        "h": 9,
        "w": 12,
        "x": 0,
        "y": 0
      },
      "id": 2,
      "maxPerRow": 2,
      "options": {
        "legend": {
          "calcs": [
            "mean",
            "max",
            "min"
          ],
          "displayMode": "table",
          "placement": "right",
          "showLegend": true
        },
        "tooltip": {
          "mode": "multi",
          "sort": "none"
        }
      },
      "pluginVersion": "10.0.2",
      "repeat": "Queries",
      "repeatDirection": "h",
      "targets": [
        {
          "datasource": {
            "uid": "$Datasource"
          },
          "refId": "A",
          "target": "aliasByNode(brocade.fos2graphite.stats.query.*.$Queries.duration, 4)",
          "textEditor": true
        }
      ],
      "title": "HTTP response time query: $Queries",
      "type": "timeseries"
    }
  ],
  "refresh": false,
  "schemaVersion": 38,
  "style": "dark",
  "tags": [
    "fos2graphite"
  ],
  "templating": {
    "list": [
      {
        "current": {
          "selected": false,
          "text": "Graphite",
          "value": "Graphite"
        },
        "hide": 0,
        "includeAll": false,
        "multi": false,
        "name": "Datasource",
        "options": [],
        "query": "graphite",
        "queryValue": "",
        "refresh": 1,
        "regex": "",
        "skipUrlSync": false,
        "type": "datasource"
      },
      {
        "current": {},
        "datasource": {
          "type": "graphite",
          "uid": "${DS_GRAPHITE}"
        },
        "definition": "brocade.fos2graphite.stats.query.*.*",
        "hide": 2,
        "includeAll": true,
        "multi": true,
        "name": "Queries",
        "options": [],
        "query": {
          "queryType": "Default",
          "refId": "A",
          "target": "brocade.fos2graphite.stats.query.*.*"
        },
        "refresh": 2,
        "regex": "",
        "skipUrlSync": false,
        "sort": 1,
        "type": "query"
      }
    ]
  },
  "time": {
    "from": "now-6h",
    "to": "now"
  },
  "timepicker": {},
  "timezone": "",
  "title": "Brocade: fos2graphite statistics",
  "uid": "AKyp37bGz",
  "version": 2,
  "weekStart": ""
}